sensingsp/__init__.py
sensingsp/config.py
sensingsp/constants.py
sensingsp/camera/__init__.py
sensingsp/camera/utils.py
sensingsp/environment/__init__.py
sensingsp/environment/environment.py
sensingsp/integratedSensorSuite/__init__.py
sensingsp/integratedSensorSuite/integratedSensorSuite.py
sensingsp/lidar/__init__.py
sensingsp/lidar/utils.py
sensingsp/probe/__init__.py
sensingsp/probe/utils.py
sensingsp/radar/__init__.py
sensingsp/radar/collector/__init__.py
sensingsp/radar/fmcwWaveform/__init__.py
sensingsp/radar/radiator/__init__.py
sensingsp/radar/transmitter/__init__.py
sensingsp/radar/utils/__init__.py
sensingsp/radar/utils/mimo.py
sensingsp/radar/utils/radarutils.py
sensingsp/radar/utils/rss.py
sensingsp/raytracing/BlenderGeometry.py
sensingsp/raytracing/RayTracingFunctions.py
sensingsp/raytracing/__init__.py
sensingsp/raytracing/raytracing.py
sensingsp/ris/__init__.py
sensingsp/ris/utils.py
sensingsp/sonar/__init__.py
sensingsp/utils/__init__.py
sensingsp/utils/blenderUI.py
sensingsp/utils/output2matlab.py
sensingsp/utils/stochastics.py
sensingsp/utils/utils.py
sensingsp/visualization/__init__.py
sensingsp/visualization/videoGrid.py
sensingsp/visualization/visualization.py
Sensing_Signal_Processing-0.1.0.dist-info/LICENSE
Sensing_Signal_Processing-0.1.0.dist-info/METADATA
Sensing_Signal_Processing-0.1.0.dist-info/WHEEL
Sensing_Signal_Processing-0.1.0.dist-info/entry_points.txt
Sensing_Signal_Processing-0.1.0.dist-info/top_level.txt
Sensing_Signal_Processing-0.1.0.dist-info/RECORD
