Metadata-Version: 2.1
Name: Sensing-Signal-Processing
Version: 0.1.0
Summary: SensingSP™ is a Blender-based open-source library for simulating the electromagnetic based sensing systems and signal processing algorithms implementations.
Home-page: https://gitlab.com/sparc-snt/sensing-signal-processing
Author: Moein Ahmadi
Author-email: moein.ahmadi@uni.lu, gmoein@gmail.com
License: MIT
Classifier: Development Status :: 3 - Alpha
Classifier: Intended Audience :: Developers
Classifier: Topic :: Software Development :: Build Tools
Classifier: License :: OSI Approved :: MIT License
Classifier: Programming Language :: Python :: 3
Classifier: Programming Language :: Python :: 3.7
Classifier: Programming Language :: Python :: 3.8
Classifier: Programming Language :: Python :: 3.9
Classifier: Programming Language :: Python :: 3.10
Requires-Python: >=3.7
License-File: LICENSE
Requires-Dist: bpy (==4.0.0)
Requires-Dist: certifi (==2024.7.4)
Requires-Dist: charset-normalizer (==3.3.2)
Requires-Dist: contourpy (==1.2.1)
Requires-Dist: cycler (==0.12.1)
Requires-Dist: Cython (==3.0.11)
Requires-Dist: fonttools (==4.53.1)
Requires-Dist: idna (==3.7)
Requires-Dist: kiwisolver (==1.4.5)
Requires-Dist: llvmlite (==0.43.0)
Requires-Dist: mathutils (==3.3.0)
Requires-Dist: matplotlib (==3.9.1.post1)
Requires-Dist: numba (==0.60.0)
Requires-Dist: numpy (==2.0.1)
Requires-Dist: opencv-python (==4.10.0.84)
Requires-Dist: packaging (==24.1)
Requires-Dist: pillow (==10.4.0)
Requires-Dist: pyparsing (==3.1.2)
Requires-Dist: python-dateutil (==2.9.0.post0)
Requires-Dist: requests (==2.32.3)
Requires-Dist: scipy (==1.14.0)
Requires-Dist: six (==1.16.0)
Requires-Dist: urllib3 (==2.2.2)
Requires-Dist: zstandard (==0.23.0)
